[
  {
    "discountPercentage": 50,
    "endDate": "2023-06-13T18:30:00.000Z",
    "isFree": false,
    "originalPrice": 629,
    "slug": "aftertime-1ca584",
    "startDate": "2023-05-30T18:30:00.000Z",
    "title": "Aftertime"
  },
  {
    "discountPercentage": 75,
    "endDate": "2023-08-03T15:00:00.000Z",
    "isFree": false,
    "originalPrice": 1349,
    "slug": "alekon-b2faec",
    "startDate": "2023-07-20T15:00:00.000Z",
    "title": "Alekon"
  },
  {
    "discountPercentage": 15,
    "endDate": "2023-06-12T14:00:00.000Z",
    "isFree": false,
    "originalPrice": 2699,
    "slug": "bramble-the-mountain-king-c0d1c6",
    "startDate": "2023-06-05T14:00:00.000Z",
    "title": "Bramble The Mountain King"
  },
  {
    "discountPercentage": 85,
    "endDate": "2023-08-02T04:00:00.000Z",
    "isFree": false,
    "originalPrice": 1998,
    "slug": "bud-spencer-and-terence-hill-slaps-and-beans-0bdb3b",
    "startDate": "2023-06-16T04:00:00.000Z",
    "title": "Bud Spencer and Terence Hill - Slaps and Beans"
  },
  {
    "discountPercentage": 40,
    "endDate": "2023-06-12T13:00:00.000Z",
    "isFree": false,
    "originalPrice": 269,
    "slug": "busway-islands-puzzle-91287d",
    "startDate": "2023-06-05T13:00:00.000Z",
    "title": "Busway Islands - Puzzle"
  },
  {
    "discountPercentage": 40,
    "endDate": "2023-08-03T15:00:00.000Z",
    "isFree": false,
    "originalPrice": 269,
    "slug": "busway-islands-puzzle-91287d",
    "startDate": "2023-07-20T15:00:00.000Z",
    "title": "Busway Islands - Puzzle"
  },
  {
    "discountPercentage": 70,
    "endDate": "2023-06-05T14:00:00.000Z",
    "isFree": false,
    "originalPrice": 1199,
    "slug": "deathrun-tv-db074f",
    "startDate": "2023-05-29T14:00:00.000Z",
    "title": "DEATHRUN TV"
  },
  {
    "discountPercentage": 20,
    "endDate": "2023-06-15T15:00:00.000Z",
    "isFree": false,
    "originalPrice": 5999,
    "slug": "dead-island-2",
    "startDate": "2023-06-06T15:00:00.000Z",
    "title": "Dead Island 2"
  },
  {
    "discountPercentage": 50,
    "endDate": "2023-06-21T15:00:00.000Z",
    "isFree": false,
    "originalPrice": 1999,
    "slug": "dead-by-daylight",
    "startDate": "2023-06-07T15:00:00.000Z",
    "title": "Dead by Daylight"
  },
  {
    "discountPercentage": 25,
    "endDate": "2023-06-15T13:00:00.000Z",
    "isFree": false,
    "originalPrice": 2999,
    "slug": "disney-dreamlight-valley",
    "startDate": "2023-06-02T13:00:00.000Z",
    "title": "Disney Dreamlight Valley"
  },
  {
    "discountPercentage": 10,
    "endDate": "2023-08-03T15:00:00.000Z",
    "isFree": false,
    "originalPrice": 1619,
    "slug": "elegies-aya-17c3f1",
    "startDate": "2023-07-20T15:00:00.000Z",
    "title": "ELEGIES Aya"
  },
  {
    "discountPercentage": 10,
    "endDate": "2023-09-28T15:00:00.000Z",
    "isFree": false,
    "originalPrice": 1619,
    "slug": "elegies-aya-17c3f1",
    "startDate": "2023-09-14T15:00:00.000Z",
    "title": "ELEGIES Aya"
  },
  {
    "discountPercentage": 15,
    "endDate": "2024-01-11T16:00:00.000Z",
    "isFree": false,
    "originalPrice": 1619,
    "slug": "elegies-aya-17c3f1",
    "startDate": "2023-12-21T16:00:00.000Z",
    "title": "ELEGIES Aya"
  },
  {
    "discountPercentage": 70,
    "endDate": "2023-06-05T14:00:00.000Z",
    "isFree": false,
    "originalPrice": 1699,
    "slug": "foreclosed",
    "startDate": "2023-05-29T14:00:00.000Z",
    "title": "FORECLOSED"
  },
  {
    "discountPercentage": 50,
    "endDate": "2023-06-28T19:00:00.000Z",
    "isFree": false,
    "originalPrice": 999,
    "slug": "flat-heroes-fec628",
    "startDate": "2023-06-16T19:00:00.000Z",
    "title": "Flat Heroes"
  },
  {
    "discountPercentage": 50,
    "endDate": "2023-07-13T17:00:00.000Z",
    "isFree": false,
    "originalPrice": 5999,
    "slug": "football-manager-2023",
    "startDate": "2023-06-22T17:00:00.000Z",
    "title": "Football Manager 2023"
  },
  {
    "discountPercentage": 25,
    "endDate": "2023-06-05T17:00:00.000Z",
    "isFree": false,
    "originalPrice": 719,
    "slug": "fortune-follow-the-mansion-bad0b2",
    "startDate": "2023-05-29T17:00:00.000Z",
    "title": "Fortune Follow: The Mansion"
  },
  {
    "discountPercentage": 25,
    "endDate": "2023-08-03T15:00:00.000Z",
    "isFree": false,
    "originalPrice": 719,
    "slug": "fortune-follow-the-mansion-bad0b2",
    "startDate": "2023-07-20T15:00:00.000Z",
    "title": "Fortune Follow: The Mansion"
  },
  {
    "discountPercentage": 25,
    "endDate": "2023-09-12T15:00:00.000Z",
    "isFree": false,
    "originalPrice": 719,
    "slug": "fortune-follow-the-mansion-bad0b2",
    "startDate": "2023-09-05T15:00:00.000Z",
    "title": "Fortune Follow: The Mansion"
  },
  {
    "discountPercentage": 50,
    "endDate": "2023-10-24T15:00:00.000Z",
    "isFree": false,
    "originalPrice": 719,
    "slug": "fortune-follow-the-mansion-bad0b2",
    "startDate": "2023-10-17T15:00:00.000Z",
    "title": "Fortune Follow: The Mansion"
  },
  {
    "discountPercentage": 50,
    "endDate": "2023-12-05T16:00:00.000Z",
    "isFree": false,
    "originalPrice": 719,
    "slug": "fortune-follow-the-mansion-bad0b2",
    "startDate": "2023-11-28T16:00:00.000Z",
    "title": "Fortune Follow: The Mansion"
  },
  {
    "discountPercentage": 60,
    "endDate": "2023-06-20T15:00:00.000Z",
    "isFree": false,
    "originalPrice": 899,
    "slug": "fusion-paradox-31b28a",
    "startDate": "2023-06-18T22:00:00.000Z",
    "title": "Fusion Paradox"
  },
  {
    "discountPercentage": 60,
    "endDate": "2023-08-03T15:00:00.000Z",
    "isFree": false,
    "originalPrice": 899,
    "slug": "fusion-paradox-31b28a",
    "startDate": "2023-07-20T15:00:00.000Z",
    "title": "Fusion Paradox"
  },
  {
    "discountPercentage": 34,
    "endDate": "2023-07-06T21:00:00.000Z",
    "isFree": false,
    "originalPrice": 269,
    "slug": "gold-rush-classic-34d7d5",
    "startDate": "2023-06-29T09:00:00.000Z",
    "title": "Gold Rush! Classic"
  },
  {
    "discountPercentage": 50,
    "endDate": "2023-06-05T13:00:00.000Z",
    "isFree": false,
    "originalPrice": 899,
    "slug": "heroines-of-swords-and-spells-0db5cd",
    "startDate": "2023-05-29T13:00:00.000Z",
    "title": "Heroines of Swords & Spells + Green Furies DLC"
  },
  {
    "discountPercentage": 30,
    "endDate": "2023-08-03T15:00:00.000Z",
    "isFree": false,
    "originalPrice": 399,
    "slug": "im-looking-for-3024-people-1cdae4",
    "startDate": "2023-07-20T15:00:00.000Z",
    "title": "I'm looking for 3024 people"
  },
  {
    "discountPercentage": 50,
    "endDate": "2023-08-03T15:00:00.000Z",
    "isFree": false,
    "originalPrice": 1529,
    "slug": "infindustry-cccc40",
    "startDate": "2023-07-20T15:00:00.000Z",
    "title": "Infindustry"
  },
  {
    "discountPercentage": 50,
    "endDate": "2023-09-28T15:00:00.000Z",
    "isFree": false,
    "originalPrice": 1529,
    "slug": "infindustry-cccc40",
    "startDate": "2023-09-14T15:00:00.000Z",
    "title": "Infindustry"
  },
  {
    "discountPercentage": 50,
    "endDate": "2023-11-28T16:00:00.000Z",
    "isFree": false,
    "originalPrice": 1529,
    "slug": "infindustry-cccc40",
    "startDate": "2023-11-21T16:00:00.000Z",
    "title": "Infindustry"
  },
  {
    "discountPercentage": 67,
    "endDate": "2023-06-05T13:00:00.000Z",
    "isFree": false,
    "originalPrice": 0,
    "slug": "judas",
    "startDate": "2023-05-29T13:00:00.000Z",
    "title": "Judas"
  },
  {
    "discountPercentage": 50,
    "endDate": "2023-06-05T13:00:00.000Z",
    "isFree": false,
    "originalPrice": 179,
    "slug": "kill-fish-1c85e9",
    "startDate": "2023-05-29T13:00:00.000Z",
    "title": "Kill Fish"
  },
  {
    "discountPercentage": 66,
    "endDate": "2023-08-07T15:00:00.000Z",
    "isFree": false,
    "originalPrice": 1699,
    "slug": "lego-builders-journey",
    "startDate": "2023-07-31T15:00:00.000Z",
    "title": "LEGO\u00ae Builder's Journey"
  },
  {
    "discountPercentage": 15,
    "endDate": "2023-06-22T16:00:00.000Z",
    "isFree": false,
    "originalPrice": 2299,
    "slug": "layers-of-fear",
    "startDate": "2023-06-15T16:00:00.000Z",
    "title": "Layers of Fear: Masterpiece Edition"
  },
  {
    "discountPercentage": 40,
    "endDate": "2023-07-20T00:00:00.000Z",
    "isFree": false,
    "originalPrice": 449,
    "slug": "life-after-death-b4e964",
    "startDate": "2023-06-25T00:00:00.000Z",
    "title": "Life After Death"
  },
  {
    "discountPercentage": 35,
    "endDate": "2023-06-07T04:00:00.000Z",
    "isFree": false,
    "originalPrice": 359,
    "slug": "musynx-fb5190",
    "startDate": "2023-05-31T04:00:00.000Z",
    "title": "MUSYNX"
  },
  {
    "discountPercentage": 30,
    "endDate": "2023-06-07T13:00:00.000Z",
    "isFree": false,
    "originalPrice": 359,
    "slug": "match-village-5f41dd",
    "startDate": "2023-06-01T13:00:00.000Z",
    "title": "Match Village"
  },
  {
    "discountPercentage": 30,
    "endDate": "2023-08-03T15:00:00.000Z",
    "isFree": false,
    "originalPrice": 359,
    "slug": "match-village-5f41dd",
    "startDate": "2023-07-20T15:00:00.000Z",
    "title": "Match Village"
  },
  {
    "discountPercentage": 70,
    "endDate": "2023-06-05T14:00:00.000Z",
    "isFree": false,
    "originalPrice": 1399,
    "slug": "monster-harvest-75f018",
    "startDate": "2023-05-29T14:00:00.000Z",
    "title": "Monster Harvest"
  },
  {
    "discountPercentage": 100,
    "endDate": "2023-06-08T15:00:00.000Z",
    "isFree": true,
    "originalPrice": 0,
    "slug": "mystery-game-5",
    "startDate": "2023-06-01T15:00:00.000Z",
    "title": "Mystery Game"
  },
  {
    "discountPercentage": 33,
    "endDate": "2023-06-18T14:30:00.000Z",
    "isFree": false,
    "originalPrice": 1349,
    "slug": "one-more-dungeon-2-532228",
    "startDate": "2023-06-09T14:30:00.000Z",
    "title": "One More Dungeon 2"
  },
  {
    "discountPercentage": 30,
    "endDate": "2023-08-03T15:00:00.000Z",
    "isFree": false,
    "originalPrice": 899,
    "slug": "outcore-desktop-adventure-eb3aff",
    "startDate": "2023-07-20T15:00:00.000Z",
    "title": "Outcore - Desktop Adventure"
  },
  {
    "discountPercentage": 10,
    "endDate": "2023-06-06T12:00:00.000Z",
    "isFree": false,
    "originalPrice": 1349,
    "slug": "return-to-grace-92a75a",
    "startDate": "2023-05-30T13:00:00.000Z",
    "title": "Return to Grace"
  },
  {
    "discountPercentage": 30,
    "endDate": "2023-06-08T10:00:00.000Z",
    "isFree": false,
    "originalPrice": 899,
    "slug": "search-de9485",
    "startDate": "2023-06-01T10:00:00.000Z",
    "title": "Search"
  },
  {
    "discountPercentage": 30,
    "endDate": "2023-08-03T15:00:00.000Z",
    "isFree": false,
    "originalPrice": 4999,
    "slug": "shinchan-me-and-the-professor-on-summer-vacation-bb7bad",
    "startDate": "2023-07-20T15:00:00.000Z",
    "title": "Shin-chan Me and the Professor on Summer Vacation"
  },
  {
    "discountPercentage": 50,
    "endDate": "2023-06-15T04:00:00.000Z",
    "isFree": false,
    "originalPrice": 899,
    "slug": "shotgun-farmers-d9f3f0",
    "startDate": "2023-06-01T04:00:00.000Z",
    "title": "Shotgun Farmers"
  },
  {
    "discountPercentage": 15,
    "endDate": "2023-06-19T14:00:00.000Z",
    "isFree": false,
    "originalPrice": 2499,
    "slug": "smalland",
    "startDate": "2023-06-12T14:00:00.000Z",
    "title": "Smalland: Survive the Wilds"
  },
  {
    "discountPercentage": 66,
    "endDate": "2023-07-10T14:00:00.000Z",
    "isFree": false,
    "originalPrice": 1599,
    "slug": "spirit-of-the-north-f58a66",
    "startDate": "2023-07-03T14:00:00.000Z",
    "title": "Spirit of the North"
  },
  {
    "discountPercentage": 50,
    "endDate": "2023-06-10T19:00:00.000Z",
    "isFree": false,
    "originalPrice": 1799,
    "slug": "strawhart-776f4d",
    "startDate": "2023-05-30T06:00:00.000Z",
    "title": "Strawhart"
  },
  {
    "discountPercentage": 50,
    "endDate": "2023-08-03T15:00:00.000Z",
    "isFree": false,
    "originalPrice": 1799,
    "slug": "strawhart-776f4d",
    "startDate": "2023-07-20T15:00:00.000Z",
    "title": "Strawhart"
  },
  {
    "discountPercentage": 30,
    "endDate": "2023-06-25T14:00:00.000Z",
    "isFree": false,
    "originalPrice": 2499,
    "slug": "strayed-lights-351d29",
    "startDate": "2023-06-13T14:00:00.000Z",
    "title": "Strayed Lights"
  },
  {
    "discountPercentage": 20,
    "endDate": "2023-06-29T04:00:00.000Z",
    "isFree": false,
    "originalPrice": 719,
    "slug": "suicide-guy-9f7963",
    "startDate": "2023-06-14T04:00:00.000Z",
    "title": "Suicide Guy"
  },
  {
    "discountPercentage": 20,
    "endDate": "2023-06-18T16:00:00.000Z",
    "isFree": false,
    "originalPrice": 899,
    "slug": "super-alloy-ranger-4252cc",
    "startDate": "2023-06-04T16:00:00.000Z",
    "title": "Super Alloy Ranger"
  },
  {
    "discountPercentage": 20,
    "endDate": "2023-08-03T15:00:00.000Z",
    "isFree": false,
    "originalPrice": 899,
    "slug": "super-alloy-ranger-4252cc",
    "startDate": "2023-07-20T15:00:00.000Z",
    "title": "Super Alloy Ranger"
  },
  {
    "discountPercentage": 50,
    "endDate": "2023-08-03T15:00:00.000Z",
    "isFree": false,
    "originalPrice": 809,
    "slug": "switchball-hd-6d3802",
    "startDate": "2023-07-20T15:00:00.000Z",
    "title": "Switchball HD"
  },
  {
    "discountPercentage": 50,
    "endDate": "2023-08-03T15:00:00.000Z",
    "isFree": false,
    "originalPrice": 399,
    "slug": "system-purge-9ab7b7",
    "startDate": "2023-07-20T15:00:00.000Z",
    "title": "System Purge"
  },
  {
    "discountPercentage": 70,
    "endDate": "2023-09-24T16:00:00.000Z",
    "isFree": false,
    "originalPrice": 1599,
    "slug": "toem",
    "startDate": "2023-09-11T16:00:00.000Z",
    "title": "TOEM"
  },
  {
    "discountPercentage": 50,
    "endDate": "2023-06-04T16:00:00.000Z",
    "isFree": false,
    "originalPrice": 1399,
    "slug": "tales-of-the-neon-sea",
    "startDate": "2023-05-29T16:00:00.000Z",
    "title": "Tales of the Neon Sea"
  },
  {
    "discountPercentage": 25,
    "endDate": "2023-06-28T04:00:00.000Z",
    "isFree": false,
    "originalPrice": 359,
    "slug": "tear-of-time-lost-memory-add761",
    "startDate": "2023-06-21T04:00:00.000Z",
    "title": "Tear of Time - Lost memory"
  },
  {
    "discountPercentage": 65,
    "endDate": "2023-08-03T15:00:00.000Z",
    "isFree": false,
    "originalPrice": 1799,
    "slug": "the-inheritance-of-crimson-manor-81bc67",
    "startDate": "2023-07-20T15:00:00.000Z",
    "title": "The Inheritance of Crimson Manor"
  },
  {
    "discountPercentage": 70,
    "endDate": "2023-09-12T15:00:00.000Z",
    "isFree": false,
    "originalPrice": 1799,
    "slug": "the-inheritance-of-crimson-manor-81bc67",
    "startDate": "2023-09-05T15:00:00.000Z",
    "title": "The Inheritance of Crimson Manor"
  },
  {
    "discountPercentage": 40,
    "endDate": "2023-06-15T12:00:00.000Z",
    "isFree": false,
    "originalPrice": 2999,
    "slug": "the-riftbreaker",
    "startDate": "2023-05-29T12:00:00.000Z",
    "title": "The Riftbreaker"
  },
  {
    "discountPercentage": 15,
    "endDate": "2023-06-11T07:00:00.000Z",
    "isFree": false,
    "originalPrice": 1799,
    "slug": "the-unbeatable-path-8af8fc",
    "startDate": "2023-06-01T07:00:00.000Z",
    "title": "The Unbeatable Path"
  },
  {
    "discountPercentage": 66,
    "endDate": "2023-06-26T14:00:00.000Z",
    "isFree": false,
    "originalPrice": 1599,
    "slug": "time-on-frog-island-b3ad0d",
    "startDate": "2023-06-19T14:00:00.000Z",
    "title": "Time on Frog Island"
  },
  {
    "discountPercentage": 50,
    "endDate": "2023-08-15T14:00:00.000Z",
    "isFree": false,
    "originalPrice": 1399,
    "slug": "timelie",
    "startDate": "2023-08-01T14:00:00.000Z",
    "title": "Timelie - Game of the Year Edition"
  },
  {
    "discountPercentage": 10,
    "endDate": "2023-06-06T04:00:00.000Z",
    "isFree": false,
    "originalPrice": 1799,
    "slug": "to-hell-with-the-ugly-86ee3f",
    "startDate": "2023-05-30T04:00:00.000Z",
    "title": "To Hell With The Ugly"
  },
  {
    "discountPercentage": 20,
    "endDate": "2023-07-18T14:00:00.000Z",
    "isFree": false,
    "originalPrice": 719,
    "slug": "tracks-of-triumph-7b2685",
    "startDate": "2023-06-18T14:00:00.000Z",
    "title": "Tracks of Triumph"
  },
  {
    "discountPercentage": 20,
    "endDate": "2023-06-03T16:00:00.000Z",
    "isFree": false,
    "originalPrice": 719,
    "slug": "tracks-of-triumph-summertime-001c7b",
    "startDate": "2023-05-27T16:00:00.000Z",
    "title": "Tracks of Triumph: Summertime"
  },
  {
    "discountPercentage": 20,
    "endDate": "2023-06-15T17:00:00.000Z",
    "isFree": false,
    "originalPrice": 1399,
    "slug": "travellers-rest-c115d1",
    "startDate": "2023-06-01T17:00:00.000Z",
    "title": "Travellers Rest"
  },
  {
    "discountPercentage": 35,
    "endDate": "2023-08-03T15:00:00.000Z",
    "isFree": false,
    "originalPrice": 629,
    "slug": "voodoo-kid-05b29a",
    "startDate": "2023-07-20T15:00:00.000Z",
    "title": "Voodoo Kid"
  },
  {
    "discountPercentage": 40,
    "endDate": "2023-06-05T11:00:00.000Z",
    "isFree": false,
    "originalPrice": 899,
    "slug": "world-of-contraptions-6dbc07",
    "startDate": "2023-05-29T11:00:00.000Z",
    "title": "World of Contraptions"
  },
  {
    "discountPercentage": 40,
    "endDate": "2023-06-05T01:00:00.000Z",
    "isFree": false,
    "originalPrice": 449,
    "slug": "yodanji-5a175c",
    "startDate": "2023-05-29T01:00:00.000Z",
    "title": "Yodanji"
  }
]